mojo/waiting/__init__.py
mojo/waiting/constants.py
mojo/waiting/waitfunction.py
mojo/waiting/waitmodel.py
mojo_waiting-2.0.1.dist-info/LICENSE.txt
mojo_waiting-2.0.1.dist-info/METADATA
mojo_waiting-2.0.1.dist-info/WHEEL
mojo_waiting-2.0.1.dist-info/RECORD
