Metadata-Version: 2.1
Name: mojo-waiting
Version: 2.0.1
Summary: Automation Mojo Waiting Module
Home-page: http://automationmojo.com
License: LICENSE.txt
Keywords: python
Author: Myron Walker
Author-email: myron.walker@gmail.com
Requires-Python: >=3.9,<4.0
Classifier: License :: OSI Approved :: MIT License
Classifier: License :: Other/Proprietary License
Classifier: Operating System :: POSIX
Classifier: Programming Language :: Python :: 3
Classifier: Programming Language :: Python :: 3.9
Classifier: Programming Language :: Python :: 3.10
Classifier: Programming Language :: Python :: 3.11
Classifier: Programming Language :: Python :: 3.12
Project-URL: Repository, https://github.com/automationmojo/mojo-waiting
